astrotoolz/__init__.py
astrotoolz/app/__init__.py
astrotoolz/app/main_dasa.py
astrotoolz/app/main_gann.py
astrotoolz/app/main_horoscope.py
astrotoolz/app/main_timeline_new.py
astrotoolz/app/main_tl_mer.py
astrotoolz/app/resources/tv_template.txt
astrotoolz/core/__init__.py
astrotoolz/core/angles/__init__.py
astrotoolz/core/angles/angle.py
astrotoolz/core/angles/angle_factory.py
astrotoolz/core/angles/angle_target_calculator.py
astrotoolz/core/enums.py
astrotoolz/core/ephemeris/__init__.py
astrotoolz/core/ephemeris/swisseph_api.py
astrotoolz/core/events/__init__.py
astrotoolz/core/events/aspect.py
astrotoolz/core/events/astro_event.py
astrotoolz/core/events/factory/aspect_factory.py
astrotoolz/core/events/factory/extreme_event_factory.py
astrotoolz/core/events/factory/positional_event_factory.py
astrotoolz/core/events/orb_map.py
astrotoolz/core/points.py
astrotoolz/core/positions/__init__.py
astrotoolz/core/positions/base_position.py
astrotoolz/core/positions/factory/geo_factory.py
astrotoolz/core/positions/factory/helio_factory.py
astrotoolz/core/positions/factory/position_factory.py
astrotoolz/core/positions/geo_position.py
astrotoolz/core/positions/helio_position.py
astrotoolz/core/units/__init__.py
astrotoolz/core/units/degree.py
astrotoolz/core/units/degree_converter.py
astrotoolz/core/units/degree_range.py
astrotoolz/core/units/dms.py
astrotoolz/core/zodiac/__init__.py
astrotoolz/core/zodiac/division.py
astrotoolz/core/zodiac/mapped_geo_position.py
astrotoolz/core/zodiac/mapped_helio_position.py
astrotoolz/core/zodiac/mapped_position.py
astrotoolz/core/zodiac/mapper/geo_mapper.py
astrotoolz/core/zodiac/mapper/helio_mapper.py
astrotoolz/core/zodiac/mapper/position_mapper.py
astrotoolz/core/zodiac/tropical_attributes.py
astrotoolz/core/zodiac/vedic_attributes.py
astrotoolz/de421.bsp
astrotoolz/out/__init__.py
astrotoolz/out/file.py
astrotoolz/out/tv.py
astrotoolz/tools/__init__.py
astrotoolz/tools/dasa/dasa.py
astrotoolz/tools/dasa/dasa_factory.py
astrotoolz-0.1.4.dist-info/METADATA
astrotoolz-0.1.4.dist-info/WHEEL
astrotoolz-0.1.4.dist-info/RECORD
