Metadata-Version: 2.1
Name: astrotoolz
Version: 0.1.4
Summary: 
Author: Your Name
Author-email: you@example.com
Requires-Python: >=3.12,<4.0
Classifier: Programming Language :: Python :: 3
Classifier: Programming Language :: Python :: 3.12
Requires-Dist: Requests (==2.31.0)
Requires-Dist: pandas (>=2.1.4,<3.0.0)
Requires-Dist: pyhumps (>=3.8.0,<4.0.0)
Requires-Dist: pyswisseph (==2.10.3.2)
Requires-Dist: pytz (==2023.3.post1)
Requires-Dist: scipy (==1.11.4)
Requires-Dist: swisseph (==0.0.0.dev1)
Requires-Dist: timezonefinder (==6.2.0)
